{
  "cli": {
    "version": ">= 3.0.0",
    "appVersionSource": "remote"
  },
  "build": {
    "development": {
      "developmentClient": true,
      "distribution": "internal"
    },
    "preview": {
      "distribution": "internal",
      "channel": "preview"
    },
    "testflight": {
      "distribution": "store",
      "autoIncrement": true,
      "channel": "preview"
    },
    "production": {
      "distribution": "store",
      "autoIncrement": true,
      "channel": "production"
    }
  },
  "submit": {
    "testflight": {
      "ios": {
        "ascAppId": "6752588044"
      }
    },
    "production": {
      "ios": {
        "ascAppId": "6752588044"
      }
    }
  }
}
